ChangeLog
LICENSE
MANIFEST.in
README.md
README.rst
requirements.txt
setup.py
usrsvc
usrsvcd
examples/usrsvc.cfg
examples/cfg/MagicLooper.cfg
systemd/README
systemd/README~
systemd/install.sh
systemd/install.sh~
systemd/usrsvcd@.service
systemd/x/usr/lib/systemd/system/usrsvcd@.service
usrsvc.egg-info/PKG-INFO
usrsvc.egg-info/SOURCES.txt
usrsvc.egg-info/dependency_links.txt
usrsvc.egg-info/requires.txt
usrsvc.egg-info/top_level.txt
usrsvcmod/MainConfig.py
usrsvcmod/MonitoringConfig.py
usrsvcmod/Program.py
usrsvcmod/ProgramActions.py
usrsvcmod/ProgramConfig.py
usrsvcmod/UsrsvcConfig.py
usrsvcmod/__init__.py
usrsvcmod/compat.py
usrsvcmod/configcommon.py
usrsvcmod/constants.py
usrsvcmod/debug.py
usrsvcmod/logging.py
usrsvcmod/mail.py
usrsvcmod/util.py
usrsvcmod/Monitoring/ActivityFile.py
usrsvcmod/Monitoring/Factory.py
usrsvcmod/Monitoring/RSSLimit.py
usrsvcmod/Monitoring/__init__.py
usrsvcmod/client/__init__.py
usrsvcmod/client/_readme_contents.py
usrsvcmod/client/readme.py
usrsvcmod/client/usrsvc.py