Metadata-Version: 1.1
Name: usrsvc
Version: 1.5.12
Summary: A service manager for running/managing/monitoring/auto-restarting daemons and services at the user (non-root) level
Home-page: https://github.com/kata198/usrsvc
Author: Tim Savannah
Author-email: kata198@gmail.com
License: GPLv2
Keywords: usrsvc,usrsvcd,daemon,user,services,service,init,script,start,stop,restart,manage,programs,applications,supervisor,supervisord,systemd,daemontools
Platform: UNKNOWN
Classifier: Development Status :: 5 - Production/Stable
Classifier: Programming Language :: Python
Classifier: License :: OSI Approved :: GNU General Public License v2 (GPLv2)
Classifier: Programming Language :: Python :: 2
Classifier: Programming Language :: Python :: 2
Classifier: Programming Language :: Python :: 2.7
Classifier: Programming Language :: Python :: 3
Classifier: Programming Language :: Python :: 3.3
Classifier: Programming Language :: Python :: 3.4
Classifier: Programming Language :: Python :: 3.5
Classifier: Programming Language :: Python :: 3.6
Classifier: Topic :: System :: Boot :: Init
Requires: configobj
Requires: NamedAtomicLock
Requires: func_timeout
